transcriber_tool/__init__.py
transcriber_tool/cli.py
transcriber_tool-0.2.0.dist-info/METADATA
transcriber_tool-0.2.0.dist-info/WHEEL
transcriber_tool-0.2.0.dist-info/entry_points.txt
transcriber_tool-0.2.0.dist-info/licenses/LICENSE
transcriber_tool-0.2.0.dist-info/RECORD
