Metadata-Version: 2.4
Name: transcriber_tool
Version: 0.2.0
Summary: 音声ファイルをテキストに変換するCLIツール
License-File: LICENSE
Requires-Python: >=3.11
Requires-Dist: av>=11
Requires-Dist: click
Requires-Dist: ctranslate2<5,>=4.0
Requires-Dist: faster-whisper
Requires-Dist: huggingface-hub>=0.13
Requires-Dist: onnxruntime<2,>=1.14
Requires-Dist: requests
Requires-Dist: tokenizers<1,>=0.13
Requires-Dist: tqdm
